darius/__init__.py
darius/Parsing/__init__.py
darius/Parsing/http.py
darius/Parsing/websocket.py
darius/client_side/__init__.py
darius/client_side/c_types.py
darius/client_side/cscript.py
darius/client_side/status.py
darius/server/__init__.py
darius/server/cache.py
darius/server/routes.py
darius/server/server.py
darius-1.0.0.dist-info/LICENCE
darius-1.0.0.dist-info/METADATA
darius-1.0.0.dist-info/WHEEL
darius-1.0.0.dist-info/top_level.txt
darius-1.0.0.dist-info/RECORD
