Metadata-Version: 2.1
Name: darius
Version: 1.0.0
Summary: An easy library to use to host an HTTP or a Websocket server with plenty of functionality
Home-page: https://github.com/Greece4ever/darius
Author: Leonidios Megalopoutsis
Author-email: programertv633@gmail.com
License: UNKNOWN
Platform: UNKNOWN
Classifier: Programming Language :: Python :: 3
Classifier: License :: OSI Approved :: MIT License
Classifier: Operating System :: OS Independent
Requires-Python: >=3.6
